mit_cod/__init__.py
mit_cod/app.py
mit_cod/check_requirements.py
mit_cod/image_manipulation.py
mit_cod/marks_detection.py
mit_cod/marks_model.py
mit_cod/msgbox.py
mit_cod/paper_processor.py
mit_cod/perspective_correction.py
mit_cod/predictor.py
mit_cod/roi_selector.py
mit_cod/bin/AForge.Controls.dll
mit_cod/bin/AForge.Imaging.dll
mit_cod/bin/AForge.Math.dll
mit_cod/bin/AForge.Video.DirectShow.dll
mit_cod/bin/AForge.Video.dll
mit_cod/bin/AForge.dll
mit_cod/bin/CODGUI.dll
mit_cod/bin/CODGUI.pdb
mit_cod/bin/Newtonsoft.Json.dll
mit_cod/classifier/svm_digits.dat
mit_cod-1.0.5.dist-info/DESCRIPTION.rst
mit_cod-1.0.5.dist-info/METADATA
mit_cod-1.0.5.dist-info/RECORD
mit_cod-1.0.5.dist-info/WHEEL
mit_cod-1.0.5.dist-info/entry_points.txt
mit_cod-1.0.5.dist-info/metadata.json
mit_cod-1.0.5.dist-info/top_level.txt
