Metadata-Version: 2.0
Name: mit-cod
Version: 1.0.5
Summary: Course Outcome Digitizer for MIT, Manipal
Home-page: https://github.com/aharshac/MTech-CO-Digitizer
Author: Harsha Alva, Keerthivasan S.
Author-email: aharshac@gmail.com
License: MIT
Requires-Dist: imutils
Requires-Dist: pythonnet
